<?xml version="1.0" encoding="UTF-8"?>
<!DOCTYPE generatorConfiguration
        PUBLIC "-//mybatis.org//DTD MyBatis Generator Configuration 1.0//EN"
        "http://mybatis.org/dtd/mybatis-generator-config_1_0.dtd">
<generatorConfiguration>

    <classPathEntry location="/home/segeon/mysql-connector-java-5.1.39.jar"/>
    <context id="MysqlTables" targetRuntime="MyBatis3">
        <commentGenerator>
            <property name="suppressAllComments" value="false" />
        </commentGenerator>
        <jdbcConnection driverClass="com.mysql.jdbc.Driver" connectionURL="jdbc:mysql://localhost:3306/chinchilla?useSSL=false&amp;requireSSL=false" userId="root" password="admin">
        </jdbcConnection>
        <javaTypeResolver>
            <property name="forceBigDecimals" value="false"/>
        </javaTypeResolver>
        <javaModelGenerator targetPackage="com.segeon.chinchilla.server.dal.model" targetProject="src/main/java">
            <property name="enableSubPackages" value="false"/>
            <property name="trimStrings" value="true"/>
        </javaModelGenerator>
        <sqlMapGenerator targetPackage="com.segeon.chinchilla.server.dal.mapper" targetProject="src/main/resources">
            <property name="enableSubPackages" value="true"/>
        </sqlMapGenerator>
        <javaClientGenerator type="XMLMAPPER" targetPackage="com.segeon.chinchilla.server.dal.mapper" targetProject="src/main/java">
            <property name="enableSubPackages" value="false"/>
        </javaClientGenerator>
        <table schema="chinchilla" tableName="application" enableCountByExample="true" enableUpdateByExample="true" enableDeleteByExample="true" enableSelectByExample="true" selectByExampleQueryId="true">
        </table>
        <table schema="chinchilla" tableName="conf" enableCountByExample="true" enableUpdateByExample="true" enableDeleteByExample="true" enableSelectByExample="true" selectByExampleQueryId="true">
        </table>
        <table schema="chinchilla" tableName="conf_version" enableCountByExample="true" enableUpdateByExample="true" enableDeleteByExample="true" enableSelectByExample="true" selectByExampleQueryId="true">
        </table>
        <table schema="chinchilla" tableName="conf_module" enableCountByExample="true" enableUpdateByExample="true" enableDeleteByExample="true" enableSelectByExample="true" selectByExampleQueryId="true">
        </table>
        <table schema="chinchilla" tableName="module" enableCountByExample="true" enableUpdateByExample="true" enableDeleteByExample="true" enableSelectByExample="true" selectByExampleQueryId="true">
        </table>
        <table schema="chinchilla" tableName="profile" enableCountByExample="true" enableUpdateByExample="true" enableDeleteByExample="true" enableSelectByExample="true" selectByExampleQueryId="true">
        </table>
        <table schema="chinchilla" tableName="application_profile" enableCountByExample="true" enableUpdateByExample="true" enableDeleteByExample="true" enableSelectByExample="true" selectByExampleQueryId="true">
        </table>
    </context>

</generatorConfiguration>
